calculadora.py
combinatorias.py
micalcu-0.4.0.dist-info/licenses/LICENSE
micalcu-0.4.0.dist-info/METADATA
micalcu-0.4.0.dist-info/WHEEL
micalcu-0.4.0.dist-info/top_level.txt
micalcu-0.4.0.dist-info/RECORD
