Metadata-Version: 2.4
Name: micalcu
Version: 0.4.0
Summary: Calculadora y Combinatoria como paquete Python
Author-email: Pedro Shiguihara <p.shiguihara@gmail.com>
License: MIT
Project-URL: Homepage, https://github.com/pshiguihara/micalcu
Keywords: calculator,example,teaching
Requires-Python: >=3.12
License-File: LICENSE
Dynamic: license-file
